lsfm_destripe_napari/__init__.py
lsfm_destripe_napari/_reader.py
lsfm_destripe_napari/_widget.py
lsfm_destripe_napari/_writer.py
lsfm_destripe_napari/napari.yaml
lsfm_destripe_napari/_tests/__init__.py
lsfm_destripe_napari/_tests/test_reader.py
lsfm_destripe_napari/_tests/test_widget.py
lsfm_destripe_napari/_tests/test_writer.py
lsfm_destripe_napari-0.3.0.dist-info/licenses/LICENSE
lsfm_destripe_napari-0.3.0.dist-info/METADATA
lsfm_destripe_napari-0.3.0.dist-info/WHEEL
lsfm_destripe_napari-0.3.0.dist-info/entry_points.txt
lsfm_destripe_napari-0.3.0.dist-info/top_level.txt
lsfm_destripe_napari-0.3.0.dist-info/RECORD
