Metadata-Version: 2.4
Name: LSFM_destripe_napari
Version: 0.3.0
Summary: A simple plugin to destripe microscopy images in napari
Author: lennart kowitz
Author-email: lennart.kowitz@isas.de
License: 
Project-URL: Bug Tracker, https://github.com/peng-lab/lsfm_destripe_napari/issues
Project-URL: Documentation, https://github.com/peng-lab/lsfm_destripe_napari#README.md
Project-URL: Source Code, https://github.com/peng-lab/lsfm_destripe_napari
Project-URL: User Support, https://github.com/peng-lab/lsfm_destripe_napari/issues
Classifier: Development Status :: 3 - Alpha
Classifier: Framework :: napari
Classifier: Intended Audience :: Developers
Classifier: License :: OSI Approved :: BSD License
Classifier: Operating System :: OS Independent
Classifier: Programming Language :: Python
Classifier: Programming Language :: Python :: 3
Classifier: Programming Language :: Python :: 3 :: Only
Classifier: Programming Language :: Python :: 3.10
Classifier: Programming Language :: Python :: 3.11
Classifier: Programming Language :: Python :: 3.12
Classifier: Topic :: Scientific/Engineering :: Image Processing
Requires-Python: >=3.10
License-File: LICENSE
Requires-Dist: numpy
Requires-Dist: qtpy
Requires-Dist: scikit-image
Requires-Dist: bioio
Requires-Dist: leonardo_toolset
Provides-Extra: testing
Requires-Dist: tox; extra == "testing"
Requires-Dist: pytest; extra == "testing"
Requires-Dist: pytest-cov; extra == "testing"
Requires-Dist: pytest-qt; extra == "testing"
Requires-Dist: napari; extra == "testing"
Requires-Dist: pyqt5; extra == "testing"
Dynamic: license-file
